cs/app/osx/objc.py
cs.app.osx.objc-20240622.dist-info/METADATA
cs.app.osx.objc-20240622.dist-info/WHEEL
cs.app.osx.objc-20240622.dist-info/top_level.txt
cs.app.osx.objc-20240622.dist-info/RECORD
