Metadata-Version: 2.1
Name: cs.app.osx.objc
Version: 20240622
Summary: Convenience facilities for working with pyobjc (MacOSX Objective C facilities). See also: https://pyobjc.readthedocs.io/en/latest/index.html
Author-email: Cameron Simpson <cs@cskk.id.au>
License: GNU General Public License v3 or later (GPLv3+)
Project-URL: Monorepo Hg/Mercurial Mirror, https://hg.sr.ht/~cameron-simpson/css
Project-URL: Monorepo Git Mirror, https://github.com/cameron-simpson/css
Project-URL: MonoRepo Commits, https://bitbucket.org/cameron_simpson/css/commits/all
Project-URL: Source, https://github.com/cameron-simpson/css/blob/main/lib/python/cs/app/osx/objc.py
Keywords: python3
Platform: UNKNOWN
Classifier: Development Status :: 5 - Production/Stable
Classifier: Environment :: MacOS X
Classifier: Intended Audience :: Developers
Classifier: Programming Language :: Python :: 3
Classifier: Operating System :: OS Independent
Classifier: Topic :: Software Development :: Libraries :: Python Modules
Classifier: License :: OSI Approved :: GNU General Public License v3 or later (GPLv3+)
Requires-Dist: cs.dateutils >=20230210
Requires-Dist: cs.deco >=20240412
Requires-Dist: cs.logutils >=20230212
Requires-Dist: cs.obj >=20220918
Requires-Dist: cs.pfx >=20240412
Requires-Dist: pyobjc
